pandas_amazon_redshift/__init__.py
pandas_amazon_redshift/_version.py
pandas_amazon_redshift/core.py
pandas_amazon_redshift/errors.py
pandas_amazon_redshift/types.py
pandas_amazon_redshift/utils.py
samples/__init__.py
samples/read_redshift_simple.py
samples/to_redshift_simple.py
pandas_amazon_redshift-0.1.1.dist-info/AUTHORS.md
pandas_amazon_redshift-0.1.1.dist-info/LICENSE
pandas_amazon_redshift-0.1.1.dist-info/METADATA
pandas_amazon_redshift-0.1.1.dist-info/WHEEL
pandas_amazon_redshift-0.1.1.dist-info/top_level.txt
pandas_amazon_redshift-0.1.1.dist-info/RECORD
