Metadata-Version: 2.1
Name: pandas-amazon-redshift
Version: 0.1.1
Summary: Pandas interface to Amazon Redshift
Home-page: https://github.com/yutaka-kabu/pandas-amazon-redshift
Author: Yutaka Kabutoya
Author-email: y.kabutoya@gmail.com
License: BSD License
Keywords: data
Platform: UNKNOWN
Classifier: Development Status :: 2 - Pre-Alpha
Classifier: Environment :: Console
Classifier: Intended Audience :: Science/Research
Classifier: Operating System :: OS Independent
Classifier: Programming Language :: Python
Classifier: Programming Language :: Python :: 3
Classifier: Programming Language :: Python :: 3.7
Classifier: Programming Language :: Python :: 3.8
Classifier: Programming Language :: Python :: 3.9
Classifier: Topic :: Scientific/Engineering
Requires-Python: >=3.7.1
License-File: LICENSE
License-File: AUTHORS.md
Requires-Dist: setuptools
Requires-Dist: pandas (>=1.3.0)
Requires-Dist: boto3 (>=1.17.100)
Requires-Dist: botocore (>=1.20.100)
